fdbk_ruuvi_reporter/__init__.py
fdbk_ruuvi_reporter/_handler.py
fdbk_ruuvi_reporter/_topic.py
fdbk_ruuvi_reporter/_version.py
fdbk_ruuvi_reporter/main.py
fdbk_ruuvi_reporter-3.1.1.data/scripts/fdbk-ruuvi-reporter
fdbk_ruuvi_reporter-3.1.1.dist-info/METADATA
fdbk_ruuvi_reporter-3.1.1.dist-info/WHEEL
fdbk_ruuvi_reporter-3.1.1.dist-info/top_level.txt
fdbk_ruuvi_reporter-3.1.1.dist-info/RECORD
