Metadata-Version: 2.1
Name: fdbk-ruuvi-reporter
Version: 3.1.1
Summary: Ruuvitag data reporter for fdbk
Home-page: https://github.com/kangasta/fdbk_ruuvi_reporter
Author: Toni Kangas
License: UNKNOWN
Platform: UNKNOWN
Classifier: Programming Language :: Python :: 3
Classifier: License :: OSI Approved :: MIT License
Classifier: Operating System :: OS Independent
Requires-Python: >=3.6
Requires-Dist: fdbk (~=3.0)
Requires-Dist: ruuvitag-sensor (~=1.0.1)
